{
  "collapse-filter": false,
  "search": "path:Elettronica",
  "showTags": false,
  "showAttachments": false,
  "hideUnresolved": false,
  "showOrphans": true,
  "collapse-color-groups": false,
  "colorGroups": [
    {
      "query": "tag:#elettronica",
      "color": {
        "a": 1,
        "rgb": 14701138
      }
    },
    {
      "query": "tag:#algoritmiXingegneria",
      "color": {
        "a": 1,
        "rgb": 14725458
      }
    },
    {
      "query": "",
      "color": {
        "a": 1,
        "rgb": 11657298
      }
    }
  ],
  "collapse-display": false,
  "showArrow": false,
  "textFadeMultiplier": 0,
  "nodeSizeMultiplier": 1.32754677754678,
  "lineSizeMultiplier": 1.28679833679834,
  "collapse-forces": false,
  "centerStrength": 0.518713248970312,
  "repelStrength": 10,
  "linkStrength": 1,
  "linkDistance": 250,
  "scale": 1.4769860980686536,
  "close": false
}